{
  "id": "exploring_speaking_qvw",
  "title": "Exploring Speaking Huaylla Wanca Quechua",
  "author": "AmmoOS Field Library",
  "dewey": "400",
  "dewey_label": "Language",
  "ein": "H7C-SPEAK-1003990e7587",
  "format": "h7c",
  "format_version": 3,
  "book_kind": "exploring",
  "speaking_lane": true,
  "iso6393": "qvw",
  "iso6391": "",
  "language_name": "Huaylla Wanca Quechua",
  "language_status": "living",
  "embedded_figures": [],
  "manual_reader": "/field-lang-manuals",
  "h7c": "library/dewey/400-education/exploring_speaking_qvw/exploring_speaking_qvw.h7c",
  "field_path": "library/dewey/400-education/exploring_speaking_qvw/exploring_speaking_qvw.h7c",
  "github_shelf": "400-education",
  "updated": "2026-06-30T21:10:31Z"
}
