{
  "id": "exploring_speaking_baf",
  "title": "Exploring Speaking Nubaca",
  "author": "AmmoOS Field Library",
  "dewey": "400",
  "dewey_label": "Language",
  "ein": "H7C-SPEAK-e615e1385a73",
  "format": "h7c",
  "format_version": 3,
  "book_kind": "exploring",
  "speaking_lane": true,
  "iso6393": "baf",
  "iso6391": "",
  "language_name": "Nubaca",
  "language_status": "living",
  "embedded_figures": [],
  "manual_reader": "/field-lang-manuals",
  "h7c": "library/dewey/400-education/exploring_speaking_baf/exploring_speaking_baf.h7c",
  "field_path": "library/dewey/400-education/exploring_speaking_baf/exploring_speaking_baf.h7c",
  "github_shelf": "400-education",
  "updated": "2026-06-30T20:50:38Z"
}
