{
  "id": "exploring_speaking_ugy",
  "title": "Exploring Speaking Uruguayan Sign Language",
  "author": "AmmoOS Field Library",
  "dewey": "400",
  "dewey_label": "Language",
  "ein": "H7C-SPEAK-93d0fa835d2b",
  "format": "h7c",
  "format_version": 3,
  "book_kind": "exploring",
  "speaking_lane": true,
  "iso6393": "ugy",
  "iso6391": "",
  "language_name": "Uruguayan Sign Language",
  "language_status": "living",
  "embedded_figures": [],
  "manual_reader": "/field-lang-manuals",
  "h7c": "library/dewey/400-education/exploring_speaking_ugy/exploring_speaking_ugy.h7c",
  "field_path": "library/dewey/400-education/exploring_speaking_ugy/exploring_speaking_ugy.h7c",
  "github_shelf": "400-education",
  "updated": "2026-06-30T21:11:44Z"
}
