{
  "id": "exploring_speaking_srd",
  "title": "Exploring Speaking Sardinian",
  "author": "AmmoOS Field Library",
  "dewey": "400",
  "dewey_label": "Language",
  "ein": "H7C-SPEAK-0657a7c0c6f4",
  "format": "h7c",
  "format_version": 3,
  "book_kind": "exploring",
  "speaking_lane": true,
  "iso6393": "srd",
  "iso6391": "sc",
  "language_name": "Sardinian",
  "language_status": "living",
  "embedded_figures": [],
  "manual_reader": "/field-lang-manuals",
  "h7c": "library/dewey/400-education/exploring_speaking_srd/exploring_speaking_srd.h7c",
  "field_path": "library/dewey/400-education/exploring_speaking_srd/exploring_speaking_srd.h7c",
  "github_shelf": "400-education",
  "updated": "2026-06-30T21:11:00Z"
}
