{
  "id": "exploring_speaking_aum",
  "title": "Exploring Speaking Asu (Nigeria)",
  "author": "AmmoOS Field Library",
  "dewey": "400",
  "dewey_label": "Language",
  "ein": "H7C-SPEAK-b3d737351406",
  "format": "h7c",
  "format_version": 3,
  "book_kind": "exploring",
  "speaking_lane": true,
  "iso6393": "aum",
  "iso6391": "",
  "language_name": "Asu (Nigeria)",
  "language_status": "living",
  "embedded_figures": [],
  "manual_reader": "/field-lang-manuals",
  "h7c": "library/dewey/400-education/exploring_speaking_aum/exploring_speaking_aum.h7c",
  "field_path": "library/dewey/400-education/exploring_speaking_aum/exploring_speaking_aum.h7c",
  "github_shelf": "400-education",
  "updated": "2026-06-30T20:50:30Z"
}
