{
  "id": "exploring_speaking_gev",
  "title": "Exploring Speaking Eviya",
  "author": "AmmoOS Field Library",
  "dewey": "400",
  "dewey_label": "Language",
  "ein": "H7C-SPEAK-9e2ada7cdabc",
  "format": "h7c",
  "format_version": 3,
  "book_kind": "exploring",
  "speaking_lane": true,
  "iso6393": "gev",
  "iso6391": "",
  "language_name": "Eviya",
  "language_status": "living",
  "embedded_figures": [],
  "manual_reader": "/field-lang-manuals",
  "h7c": "library/dewey/400-education/exploring_speaking_gev/exploring_speaking_gev.h7c",
  "field_path": "library/dewey/400-education/exploring_speaking_gev/exploring_speaking_gev.h7c",
  "github_shelf": "400-education",
  "updated": "2026-06-30T21:03:20Z"
}
