{
  "id": "exploring_speaking_kcs",
  "title": "Exploring Speaking Koenoem",
  "author": "AmmoOS Field Library",
  "dewey": "400",
  "dewey_label": "Language",
  "ein": "H7C-SPEAK-8200995113ba",
  "format": "h7c",
  "format_version": 3,
  "book_kind": "exploring",
  "speaking_lane": true,
  "iso6393": "kcs",
  "iso6391": "",
  "language_name": "Koenoem",
  "language_status": "living",
  "embedded_figures": [],
  "manual_reader": "/field-lang-manuals",
  "h7c": "library/dewey/400-education/exploring_speaking_kcs/exploring_speaking_kcs.h7c",
  "field_path": "library/dewey/400-education/exploring_speaking_kcs/exploring_speaking_kcs.h7c",
  "github_shelf": "400-education",
  "updated": "2026-06-30T21:07:16Z"
}
