{
  "id": "exploring_speaking_ljw",
  "title": "Exploring Speaking Yirandali",
  "author": "AmmoOS Field Library",
  "dewey": "400",
  "dewey_label": "Language",
  "ein": "H7C-SPEAK-d35703df64f5",
  "format": "h7c",
  "format_version": 3,
  "book_kind": "exploring",
  "speaking_lane": true,
  "iso6393": "ljw",
  "iso6391": "",
  "language_name": "Yirandali",
  "language_status": "living",
  "embedded_figures": [],
  "manual_reader": "/field-lang-manuals",
  "h7c": "library/dewey/400-education/exploring_speaking_ljw/exploring_speaking_ljw.h7c",
  "field_path": "library/dewey/400-education/exploring_speaking_ljw/exploring_speaking_ljw.h7c",
  "github_shelf": "400-education",
  "updated": "2026-06-30T21:07:54Z"
}
