{
  "id": "exploring_speaking_thl",
  "title": "Exploring Speaking Dangaura Tharu",
  "author": "AmmoOS Field Library",
  "dewey": "400",
  "dewey_label": "Language",
  "ein": "H7C-SPEAK-70ec53168957",
  "format": "h7c",
  "format_version": 3,
  "book_kind": "exploring",
  "speaking_lane": true,
  "iso6393": "thl",
  "iso6391": "",
  "language_name": "Dangaura Tharu",
  "language_status": "living",
  "embedded_figures": [],
  "manual_reader": "/field-lang-manuals",
  "h7c": "library/dewey/400-education/exploring_speaking_thl/exploring_speaking_thl.h7c",
  "field_path": "library/dewey/400-education/exploring_speaking_thl/exploring_speaking_thl.h7c",
  "github_shelf": "400-education",
  "updated": "2026-06-30T21:11:20Z"
}
