{
  "id": "exploring_speaking_wob",
  "title": "Exploring Speaking Wè Northern",
  "author": "AmmoOS Field Library",
  "dewey": "400",
  "dewey_label": "Language",
  "ein": "H7C-SPEAK-75b6ddd5681e",
  "format": "h7c",
  "format_version": 3,
  "book_kind": "exploring",
  "speaking_lane": true,
  "iso6393": "wob",
  "iso6391": "",
  "language_name": "Wè Northern",
  "language_status": "living",
  "embedded_figures": [],
  "manual_reader": "/field-lang-manuals",
  "h7c": "library/dewey/400-education/exploring_speaking_wob/exploring_speaking_wob.h7c",
  "field_path": "library/dewey/400-education/exploring_speaking_wob/exploring_speaking_wob.h7c",
  "github_shelf": "400-education",
  "updated": "2026-06-30T21:12:04Z"
}
