{
  "name": "Hostess 7",
  "version": "1.0.7e",
  "mode": "pages-boot-terminal",
  "posture": "war-ready",
  "war_ready": true,
  "brain": false,
  "demo": false,
  "boot_command": "./Hostess7.sh boot",
  "sovereign_time_only": true,
  "pages_role": "boot_terminal_only",
  "live_surfaces": "127.0.0.1 loopback \u2014 not github.io",
  "pages_url": "https://zacharygeurts.github.io/Hostess7/",
  "repo": "https://github.com/ZacharyGeurts/Hostess7",
  "codespaces": "https://github.com/codespaces/new?hide_repo_select=true&repo=ZacharyGeurts/Hostess7",
  "boot_manifest": "/boot.json",
  "surfaces": {
    "hostess7": "http://127.0.0.1:8080/",
    "panel": "http://127.0.0.1:9477/field",
    "queen": "http://127.0.0.1:9481/world/browser.html",
    "training": "http://127.0.0.1:9488/"
  },
  "security": {
    "https": true,
    "csp": true,
    "no_secrets_in_pages": true,
    "no_brain_on_pages": true
  },
  "commands": [
    "./Hostess7.sh boot",
    "help",
    "scan",
    "surfaces",
    "codespaces"
  ],
  "updated": "2026-07-01"
}