{
  "id": "nes_somari_the_adventurer",
  "title": "Somari the Adventurer",
  "author": "Field Extensive Library",
  "dewey": "794.8",
  "format": "h7c",
  "h7c": "library/dewey/700-arts/games/nes/nes_somari_the_adventurer/nes_somari_the_adventurer.h7c",
  "cover": "/library/assets/cartridges/nes/nes_somari_the_adventurer-box.png",
  "ready": true,
  "keywords": [
    "somari",
    "adventurer",
    "field",
    "extensive",
    "library",
    "7948",
    "794.8",
    "indoor",
    "games",
    "amusements",
    "h7c",
    "700",
    "arts",
    "nes"
  ],
  "keyword_placement": {
    "title": [
      "somari",
      "adventurer"
    ],
    "author": [
      "field",
      "extensive",
      "library"
    ],
    "dewey": [
      "7948",
      "794.8",
      "indoor",
      "games",
      "amusements"
    ],
    "subject": [],
    "collection": [],
    "format": [
      "h7c"
    ],
    "shelf": [
      "700",
      "arts",
      "nes"
    ],
    "description": [],
    "auto": []
  },
  "card_id": "CAT-7948-NES-SOMARI-THE-ADVENTURE",
  "catalog_call_number": "794.8",
  "catalog_updated": "2026-06-29T11:03:55Z"
}
