{
  "id": "exploring_speaking_pgl",
  "title": "Exploring Speaking Primitive Irish",
  "author": "AmmoOS Field Library",
  "dewey": "400",
  "dewey_label": "Language",
  "ein": "H7C-SPEAK-d84f299a5002",
  "format": "h7c",
  "format_version": 3,
  "book_kind": "exploring",
  "speaking_lane": true,
  "iso6393": "pgl",
  "iso6391": "",
  "language_name": "Primitive Irish",
  "language_status": "ancient",
  "embedded_figures": [],
  "manual_reader": "/field-lang-manuals",
  "h7c": "library/dewey/400-education/exploring_speaking_pgl/exploring_speaking_pgl.h7c",
  "field_path": "library/dewey/400-education/exploring_speaking_pgl/exploring_speaking_pgl.h7c",
  "github_shelf": "400-education",
  "updated": "2026-06-30T21:10:15Z"
}
