{
  "id": "exploring_speaking_osi",
  "title": "Exploring Speaking Osing",
  "author": "AmmoOS Field Library",
  "dewey": "400",
  "dewey_label": "Language",
  "ein": "H7C-SPEAK-f2e0a558eced",
  "format": "h7c",
  "format_version": 3,
  "book_kind": "exploring",
  "speaking_lane": true,
  "iso6393": "osi",
  "iso6391": "",
  "language_name": "Osing",
  "language_status": "living",
  "embedded_figures": [],
  "manual_reader": "/field-lang-manuals",
  "h7c": "library/dewey/400-education/exploring_speaking_osi/exploring_speaking_osi.h7c",
  "field_path": "library/dewey/400-education/exploring_speaking_osi/exploring_speaking_osi.h7c",
  "github_shelf": "400-education",
  "updated": "2026-06-30T21:10:08Z"
}
