{
  "id": "exploring_speaking_nij",
  "title": "Exploring Speaking Ngaju",
  "author": "AmmoOS Field Library",
  "dewey": "400",
  "dewey_label": "Language",
  "ein": "H7C-SPEAK-3df433c28114",
  "format": "h7c",
  "format_version": 3,
  "book_kind": "exploring",
  "speaking_lane": true,
  "iso6393": "nij",
  "iso6391": "",
  "language_name": "Ngaju",
  "language_status": "living",
  "embedded_figures": [],
  "manual_reader": "/field-lang-manuals",
  "h7c": "library/dewey/400-education/exploring_speaking_nij/exploring_speaking_nij.h7c",
  "field_path": "library/dewey/400-education/exploring_speaking_nij/exploring_speaking_nij.h7c",
  "github_shelf": "400-education",
  "updated": "2026-06-30T21:09:30Z"
}
