{
  "id": "exploring_speaking_sqo",
  "title": "Exploring Speaking Sorkhei",
  "author": "AmmoOS Field Library",
  "dewey": "400",
  "dewey_label": "Language",
  "ein": "H7C-SPEAK-009b65227458",
  "format": "h7c",
  "format_version": 3,
  "book_kind": "exploring",
  "speaking_lane": true,
  "iso6393": "sqo",
  "iso6391": "",
  "language_name": "Sorkhei",
  "language_status": "living",
  "embedded_figures": [],
  "manual_reader": "/field-lang-manuals",
  "h7c": "library/dewey/400-education/exploring_speaking_sqo/exploring_speaking_sqo.h7c",
  "field_path": "library/dewey/400-education/exploring_speaking_sqo/exploring_speaking_sqo.h7c",
  "github_shelf": "400-education",
  "updated": "2026-06-30T21:10:59Z"
}
