{
  "id": "exploring_speaking_nre",
  "title": "Exploring Speaking Southern Rengma Naga",
  "author": "AmmoOS Field Library",
  "dewey": "400",
  "dewey_label": "Language",
  "ein": "H7C-SPEAK-a173f44c6352",
  "format": "h7c",
  "format_version": 3,
  "book_kind": "exploring",
  "speaking_lane": true,
  "iso6393": "nre",
  "iso6391": "",
  "language_name": "Southern Rengma Naga",
  "language_status": "living",
  "embedded_figures": [],
  "manual_reader": "/field-lang-manuals",
  "h7c": "library/dewey/400-education/exploring_speaking_nre/exploring_speaking_nre.h7c",
  "field_path": "library/dewey/400-education/exploring_speaking_nre/exploring_speaking_nre.h7c",
  "github_shelf": "400-education",
  "updated": "2026-06-30T21:09:53Z"
}
