{
  "id": "exploring_speaking_osx",
  "title": "Exploring Speaking Old Saxon",
  "author": "AmmoOS Field Library",
  "dewey": "400",
  "dewey_label": "Language",
  "ein": "H7C-SPEAK-c73fc19f471c",
  "format": "h7c",
  "format_version": 3,
  "book_kind": "exploring",
  "speaking_lane": true,
  "iso6393": "osx",
  "iso6391": "",
  "language_name": "Old Saxon",
  "language_status": "historical",
  "embedded_figures": [],
  "manual_reader": "/field-lang-manuals",
  "h7c": "library/dewey/400-education/exploring_speaking_osx/exploring_speaking_osx.h7c",
  "field_path": "library/dewey/400-education/exploring_speaking_osx/exploring_speaking_osx.h7c",
  "github_shelf": "400-education",
  "updated": "2026-06-30T21:10:08Z"
}
