{
  "schema": "field-chips-catalog-page/v1",
  "page_num": 39,
  "slug": "stack-arm-soc-pmic",
  "title": "ARM SoC PMIC Platform Stack",
  "body": "# ARM SoC PMIC Platform Stack\n\n**Platform stack:** `arm_soc_template` · **Era:** 2007–2026 · **Vendor:** ARM ecosystem · **Count:** 42\n\nMobile SoC companion template — DDRC, PMIC rail sequencing, GIC interrupt, clock/reset, pin controller, USB PHY — paired with Apple/Snapdragon/Exynos/MediaTek host dies.\n\n## Stack doctrine\n\nThis page lists every combinatorics leaf stamped `platform_stack: arm_soc_template` plus companion dies emitted from `field-cpu-companion-seed.json`. Host and guest CPUs matching the stack's `match` rules receive `always_with` linkage at combinatorics build — no manual wiring.\n\n## Manufacturing notes — companion dies\n\n- **ARM SoC DDRC Template** (ARM, 64-bit) — DDR/LPDDR memory controller — always-with host SoC\n- **ARM SoC PMIC Template** (ARM, 32-bit) — Power Management IC — buck/LDO rail sequencing\n- **ARM GIC Interrupt Ctrl** (ARM, 64-bit) — Generic Interrupt Controller — GICv3/v4 distributor\n- **ARM SoC Clock/Reset** (ARM, 32-bit) — CRU/PLL — CPU/GPU/DDR clock tree template\n- **ARM SoC Pin Controller** (ARM, 32-bit) — Pin mux + pad config — mobile SoC GPIO template\n- **ARM SoC USB PHY** (ARM, 32-bit) — USB3/Type-C PHY companion — PMIC-rail coupled\n\n## Catalog ids\n\nThe `chip_ids` array holds all **42** entries for this platform stack, sorted alphabetically. Run `field-ironclad-chips-combinatorics.py combinatronic` for path percents and imprint renders.\n\n*Stack: arm_soc_template · seed: data/field-cpu-companion-seed.json · citation: ironclad:chips:3*",
  "chip_ids": [
    "apple_a10",
    "apple_a11",
    "apple_a12",
    "apple_a13",
    "apple_a14",
    "apple_a15",
    "apple_a16",
    "apple_a17_pro",
    "apple_a18",
    "apple_a4",
    "apple_a5",
    "apple_a6",
    "apple_a7",
    "apple_a8",
    "apple_a9",
    "apple_m1",
    "apple_m1_max",
    "apple_m1_pro",
    "apple_m1_ultra",
    "apple_m2",
    "apple_m2_max",
    "apple_m2_pro",
    "apple_m2_ultra",
    "apple_m3",
    "apple_m3_max",
    "apple_m3_pro",
    "apple_m4",
    "apple_m4_max",
    "apple_m4_pro",
    "dimensity_9300",
    "dimensity_9400",
    "exynos_2400",
    "glue_arm_clk_rst",
    "glue_arm_ddrc",
    "glue_arm_gic",
    "glue_arm_pinctrl",
    "glue_arm_pmu",
    "glue_arm_usb_phy",
    "snapdragon_8_elite",
    "snapdragon_8_gen1",
    "snapdragon_8_gen2",
    "snapdragon_8_gen3"
  ],
  "chip_count": 42,
  "kind": "platform_stack",
  "family": "mobile",
  "platform_stack": "arm_soc_template",
  "era": "2007–2026",
  "combinatorics_total": 978,
  "cover": "/world/assets/combinatronic/chips/cyrix_6x86.png",
  "thumb": "/panel/assets/queen-prog-chips.png",
  "updated": "2026-06-29T14:48:47Z"
}
