{
  "id": "exploring_speaking_wol",
  "title": "Exploring Speaking Wolof",
  "author": "AmmoOS Field Library",
  "dewey": "400",
  "dewey_label": "Language",
  "ein": "H7C-SPEAK-e06805e0daa1",
  "format": "h7c",
  "format_version": 3,
  "book_kind": "exploring",
  "speaking_lane": true,
  "iso6393": "wol",
  "iso6391": "wo",
  "language_name": "Wolof",
  "language_status": "living",
  "embedded_figures": [],
  "manual_reader": "/field-lang-manuals",
  "h7c": "library/dewey/400-education/exploring_speaking_wol/exploring_speaking_wol.h7c",
  "field_path": "library/dewey/400-education/exploring_speaking_wol/exploring_speaking_wol.h7c",
  "github_shelf": "400-education",
  "updated": "2026-06-30T21:12:05Z"
}
