{
  "id": "exploring_speaking_zna",
  "title": "Exploring Speaking Zan Gula",
  "author": "AmmoOS Field Library",
  "dewey": "400",
  "dewey_label": "Language",
  "ein": "H7C-SPEAK-76052c1fe87f",
  "format": "h7c",
  "format_version": 3,
  "book_kind": "exploring",
  "speaking_lane": true,
  "iso6393": "zna",
  "iso6391": "",
  "language_name": "Zan Gula",
  "language_status": "living",
  "embedded_figures": [],
  "manual_reader": "/field-lang-manuals",
  "h7c": "library/dewey/400-education/exploring_speaking_zna/exploring_speaking_zna.h7c",
  "field_path": "library/dewey/400-education/exploring_speaking_zna/exploring_speaking_zna.h7c",
  "github_shelf": "400-education",
  "updated": "2026-06-30T21:14:51Z"
}
