{
  "id": "exploring_speaking_lsn",
  "title": "Exploring Speaking Tibetan Sign Language",
  "author": "AmmoOS Field Library",
  "dewey": "400",
  "dewey_label": "Language",
  "ein": "H7C-SPEAK-bf85c0e89564",
  "format": "h7c",
  "format_version": 3,
  "book_kind": "exploring",
  "speaking_lane": true,
  "iso6393": "lsn",
  "iso6391": "",
  "language_name": "Tibetan Sign Language",
  "language_status": "living",
  "embedded_figures": [],
  "manual_reader": "/field-lang-manuals",
  "h7c": "library/dewey/400-education/exploring_speaking_lsn/exploring_speaking_lsn.h7c",
  "field_path": "library/dewey/400-education/exploring_speaking_lsn/exploring_speaking_lsn.h7c",
  "github_shelf": "400-education",
  "updated": "2026-06-30T21:08:01Z"
}
