{
  "id": "exploring_speaking_yir",
  "title": "Exploring Speaking North Awyu",
  "author": "AmmoOS Field Library",
  "dewey": "400",
  "dewey_label": "Language",
  "ein": "H7C-SPEAK-ef09d60b0214",
  "format": "h7c",
  "format_version": 3,
  "book_kind": "exploring",
  "speaking_lane": true,
  "iso6393": "yir",
  "iso6391": "",
  "language_name": "North Awyu",
  "language_status": "living",
  "embedded_figures": [],
  "manual_reader": "/field-lang-manuals",
  "h7c": "library/dewey/400-education/exploring_speaking_yir/exploring_speaking_yir.h7c",
  "field_path": "library/dewey/400-education/exploring_speaking_yir/exploring_speaking_yir.h7c",
  "github_shelf": "400-education",
  "updated": "2026-06-30T21:13:31Z"
}
