{
  "id": "exploring_speaking_brf",
  "title": "Exploring Speaking Bira",
  "author": "AmmoOS Field Library",
  "dewey": "400",
  "dewey_label": "Language",
  "ein": "H7C-SPEAK-a94967250dc2",
  "format": "h7c",
  "format_version": 3,
  "book_kind": "exploring",
  "speaking_lane": true,
  "iso6393": "brf",
  "iso6391": "",
  "language_name": "Bira",
  "language_status": "living",
  "embedded_figures": [],
  "manual_reader": "/field-lang-manuals",
  "h7c": "library/dewey/400-education/exploring_speaking_brf/exploring_speaking_brf.h7c",
  "field_path": "library/dewey/400-education/exploring_speaking_brf/exploring_speaking_brf.h7c",
  "github_shelf": "400-education",
  "updated": "2026-06-30T20:52:05Z"
}
