{
  "id": "exploring_speaking_mvp",
  "title": "Exploring Speaking Duri",
  "author": "AmmoOS Field Library",
  "dewey": "400",
  "dewey_label": "Language",
  "ein": "H7C-SPEAK-3121b78e4c99",
  "format": "h7c",
  "format_version": 3,
  "book_kind": "exploring",
  "speaking_lane": true,
  "iso6393": "mvp",
  "iso6391": "",
  "language_name": "Duri",
  "language_status": "living",
  "embedded_figures": [],
  "manual_reader": "/field-lang-manuals",
  "h7c": "library/dewey/400-education/exploring_speaking_mvp/exploring_speaking_mvp.h7c",
  "field_path": "library/dewey/400-education/exploring_speaking_mvp/exploring_speaking_mvp.h7c",
  "github_shelf": "400-education",
  "updated": "2026-06-30T21:08:42Z"
}
