{
  "schema": "hostess7-final-eye/v1",
  "product": "Final_Eye",
  "version": "1.2.1",
  "codename": "eye-stoard",
  "queen_bridge": "NewLatest/Queen/lib/queen-eyeball.py",
  "port": 9479,
  "rule": "Hostess 7 corroborates Final_Eye eye operations — enemy discernment, heaven/hell gate, disarmament lane",
  "eye_operations": {
    "enemy": "Lie on vision path — not a people roster",
    "weapons": "Arsenal with strike/offense — discerned before salvo",
    "offense": "Directed at qualified enemy only",
    "heaven": "Zero-cost pass — no friendly fire",
    "hell": "Offense authorized when corroborated",
    "disarmament": "Depart with weapons; unwilling → removal escalates"
  },
  "eye_stoard": {
    "rule": "Secure expanding storage for field compiler witness — cap grows on demand, append-only ledger",
    "root": "Final_Eye/stoard",
    "apis": [
      "GET /api/eye/stoard",
      "POST /api/eye/stoard/witness",
      "GET /api/eye/stoard/ledger"
    ]
  },
  "apis": [
    "GET /api/eye/operations",
    "GET /api/eye/authority",
    "GET /api/eye/teach/doctrine?lesson=enemy",
    "GET /api/eye/understand?threat=provenance_mismatch",
    "GET /api/eye/stoard",
    "POST /api/eye/stoard/witness"
  ],
  "queen_world": "http://127.0.0.1:9481/world/",
  "teach_lessons": ["enemy", "operations", "disarmament", "authority", "comfort"]
}