{
  "id": "format-media_avi",
  "title": "AVI",
  "dewey": null,
  "format": "registry-entry",
  "family": "media",
  "extensions": [
    ".avi"
  ],
  "magic": null,
  "cover": "/library/assets/formats/media_avi.png",
  "updated": "2026-06-29T10:47:38Z",
  "keywords": [
    "avi",
    "registry",
    "entry",
    "005",
    "data",
    "file",
    "formats",
    "format",
    "media"
  ],
  "keyword_placement": {
    "title": [
      "avi"
    ],
    "author": [],
    "dewey": [],
    "subject": [],
    "collection": [],
    "format": [
      "registry",
      "entry"
    ],
    "shelf": [
      "005",
      "data",
      "file",
      "formats"
    ],
    "description": [],
    "auto": [
      "format",
      "media"
    ]
  },
  "card_id": "CAT-000-FORMAT-MEDIA-AVI",
  "catalog_call_number": "000",
  "catalog_updated": "2026-06-29T11:03:55Z"
}
