{
  "id": "exploring_speaking_ckr",
  "title": "Exploring Speaking Kairak",
  "author": "AmmoOS Field Library",
  "dewey": "400",
  "dewey_label": "Language",
  "ein": "H7C-SPEAK-962ffa26c9d1",
  "format": "h7c",
  "format_version": 3,
  "book_kind": "exploring",
  "speaking_lane": true,
  "iso6393": "ckr",
  "iso6391": "",
  "language_name": "Kairak",
  "language_status": "living",
  "embedded_figures": [],
  "manual_reader": "/field-lang-manuals",
  "h7c": "library/dewey/400-education/exploring_speaking_ckr/exploring_speaking_ckr.h7c",
  "field_path": "library/dewey/400-education/exploring_speaking_ckr/exploring_speaking_ckr.h7c",
  "github_shelf": "400-education",
  "updated": "2026-06-30T20:54:17Z"
}
