{
  "id": "gutenberg_republic",
  "title": "The Republic",
  "author": "Plato",
  "dewey": "100",
  "dewey_label": "Philosophy",
  "ein": "H7-FIELD-e47ae0a64185",
  "isbn_13": "",
  "gutenberg_id": "",
  "format": "H7",
  "field_path": "/media/default/HOSTESS7_TEAM/fieldstorage/textbooks/gutenberg_republic.h7",
  "github_shelf": "100-philosophy",
  "updated": "2026-06-24T03:12:05Z",
  "keywords": [
    "republic",
    "plato",
    "100",
    "philosophy",
    "h7",
    "gutenberg"
  ],
  "keyword_placement": {
    "title": [
      "republic"
    ],
    "author": [
      "plato"
    ],
    "dewey": [
      "100",
      "philosophy"
    ],
    "subject": [],
    "collection": [],
    "format": [
      "h7"
    ],
    "shelf": [],
    "description": [],
    "auto": [
      "gutenberg"
    ]
  },
  "card_id": "CAT-100-GUTENBERG-REPUBLIC",
  "catalog_call_number": "100",
  "catalog_updated": "2026-06-29T11:03:55Z"
}
