{
  "id": "exploring_speaking_tkg",
  "title": "Exploring Speaking Tesaka Malagasy",
  "author": "AmmoOS Field Library",
  "dewey": "400",
  "dewey_label": "Language",
  "ein": "H7C-SPEAK-cfc94b208601",
  "format": "h7c",
  "format_version": 3,
  "book_kind": "exploring",
  "speaking_lane": true,
  "iso6393": "tkg",
  "iso6391": "",
  "language_name": "Tesaka Malagasy",
  "language_status": "living",
  "embedded_figures": [],
  "manual_reader": "/field-lang-manuals",
  "h7c": "library/dewey/400-education/exploring_speaking_tkg/exploring_speaking_tkg.h7c",
  "field_path": "library/dewey/400-education/exploring_speaking_tkg/exploring_speaking_tkg.h7c",
  "github_shelf": "400-education",
  "updated": "2026-06-30T21:11:23Z"
}
