{
  "id": "exploring_speaking_bzs",
  "title": "Exploring Speaking Brazilian Sign Language",
  "author": "AmmoOS Field Library",
  "dewey": "400",
  "dewey_label": "Language",
  "ein": "H7C-SPEAK-0289c4efb63f",
  "format": "h7c",
  "format_version": 3,
  "book_kind": "exploring",
  "speaking_lane": true,
  "iso6393": "bzs",
  "iso6391": "",
  "language_name": "Brazilian Sign Language",
  "language_status": "living",
  "embedded_figures": [],
  "manual_reader": "/field-lang-manuals",
  "h7c": "library/dewey/400-education/exploring_speaking_bzs/exploring_speaking_bzs.h7c",
  "field_path": "library/dewey/400-education/exploring_speaking_bzs/exploring_speaking_bzs.h7c",
  "github_shelf": "400-education",
  "updated": "2026-06-30T20:53:16Z"
}
