{
  "id": "exploring_speaking_sto",
  "title": "Exploring Speaking Stoney",
  "author": "AmmoOS Field Library",
  "dewey": "400",
  "dewey_label": "Language",
  "ein": "H7C-SPEAK-08637bee67f9",
  "format": "h7c",
  "format_version": 3,
  "book_kind": "exploring",
  "speaking_lane": true,
  "iso6393": "sto",
  "iso6391": "",
  "language_name": "Stoney",
  "language_status": "living",
  "embedded_figures": [],
  "manual_reader": "/field-lang-manuals",
  "h7c": "library/dewey/400-education/exploring_speaking_sto/exploring_speaking_sto.h7c",
  "field_path": "library/dewey/400-education/exploring_speaking_sto/exploring_speaking_sto.h7c",
  "github_shelf": "400-education",
  "updated": "2026-06-30T21:11:04Z"
}
