{
  "id": "exploring_speaking_kid",
  "title": "Exploring Speaking Koshin",
  "author": "AmmoOS Field Library",
  "dewey": "400",
  "dewey_label": "Language",
  "ein": "H7C-SPEAK-fd9ee60c1d87",
  "format": "h7c",
  "format_version": 3,
  "book_kind": "exploring",
  "speaking_lane": true,
  "iso6393": "kid",
  "iso6391": "",
  "language_name": "Koshin",
  "language_status": "living",
  "embedded_figures": [],
  "manual_reader": "/field-lang-manuals",
  "h7c": "library/dewey/400-education/exploring_speaking_kid/exploring_speaking_kid.h7c",
  "field_path": "library/dewey/400-education/exploring_speaking_kid/exploring_speaking_kid.h7c",
  "github_shelf": "400-education",
  "updated": "2026-06-30T21:07:23Z"
}
