{
  "id": "exploring_speaking_dji",
  "title": "Exploring Speaking Djinang",
  "author": "AmmoOS Field Library",
  "dewey": "400",
  "dewey_label": "Language",
  "ein": "H7C-SPEAK-027797d92b11",
  "format": "h7c",
  "format_version": 3,
  "book_kind": "exploring",
  "speaking_lane": true,
  "iso6393": "dji",
  "iso6391": "",
  "language_name": "Djinang",
  "language_status": "living",
  "embedded_figures": [],
  "manual_reader": "/field-lang-manuals",
  "h7c": "library/dewey/400-education/exploring_speaking_dji/exploring_speaking_dji.h7c",
  "field_path": "library/dewey/400-education/exploring_speaking_dji/exploring_speaking_dji.h7c",
  "github_shelf": "400-education",
  "updated": "2026-06-30T20:56:52Z"
}
