{
  "id": "exploring_speaking_saj",
  "title": "Exploring Speaking Sahu",
  "author": "AmmoOS Field Library",
  "dewey": "400",
  "dewey_label": "Language",
  "ein": "H7C-SPEAK-b3a132ecdc16",
  "format": "h7c",
  "format_version": 3,
  "book_kind": "exploring",
  "speaking_lane": true,
  "iso6393": "saj",
  "iso6391": "",
  "language_name": "Sahu",
  "language_status": "living",
  "embedded_figures": [],
  "manual_reader": "/field-lang-manuals",
  "h7c": "library/dewey/400-education/exploring_speaking_saj/exploring_speaking_saj.h7c",
  "field_path": "library/dewey/400-education/exploring_speaking_saj/exploring_speaking_saj.h7c",
  "github_shelf": "400-education",
  "updated": "2026-06-30T21:10:41Z"
}
